codes.py
numerical_methods_collection-1.0.0.dist-info/METADATA
numerical_methods_collection-1.0.0.dist-info/WHEEL
numerical_methods_collection-1.0.0.dist-info/entry_points.txt
numerical_methods_collection-1.0.0.dist-info/top_level.txt
numerical_methods_collection-1.0.0.dist-info/RECORD
